jaqalpaq/scheduler/__init__.py
jaqalpaq/scheduler/scheduler.py
jaqalpaq/transpilers/__init__.py
jaqalpaq/transpilers/cirq/__init__.py
jaqalpaq/transpilers/cirq/frontend.py
jaqalpaq/transpilers/projectq/__init__.py
jaqalpaq/transpilers/projectq/frontend.py
jaqalpaq/transpilers/qiskit/__init__.py
jaqalpaq/transpilers/qiskit/frontend.py
jaqalpaq/transpilers/qiskit/gates.py
jaqalpaq/transpilers/qiskit/instance.py
jaqalpaq/transpilers/quil/__init__.py
jaqalpaq/transpilers/quil/frontend.py
jaqalpaq/transpilers/quil/ioncompiler.py
jaqalpaq/transpilers/quil/qscoutam.py
jaqalpaq/transpilers/tket/__init__.py
jaqalpaq/transpilers/tket/backend.py
jaqalpaq/transpilers/tket/frontend.py
test_JaqalPaq_extras-0.0.1.1.0.0rc2.data/data/share/jaqalpaq/tests/test_smoke.py
test_JaqalPaq_extras-0.0.1.1.0.0rc2.data/data/share/jaqalpaq/tests/scheduler/__init__.py
test_JaqalPaq_extras-0.0.1.1.0.0rc2.data/data/share/jaqalpaq/tests/scheduler/test_scheduler.py
test_JaqalPaq_extras-0.0.1.1.0.0rc2.data/data/share/jaqalpaq/tests/transpilers/__init__.py
test_JaqalPaq_extras-0.0.1.1.0.0rc2.data/data/share/jaqalpaq/tests/transpilers/cirq/__init__.py
test_JaqalPaq_extras-0.0.1.1.0.0rc2.data/data/share/jaqalpaq/tests/transpilers/cirq/test_cirq_transpiler.py
test_JaqalPaq_extras-0.0.1.1.0.0rc2.data/data/share/jaqalpaq/tests/transpilers/projectq/__init__.py
test_JaqalPaq_extras-0.0.1.1.0.0rc2.data/data/share/jaqalpaq/tests/transpilers/projectq/test_projectq_transpiler.py
test_JaqalPaq_extras-0.0.1.1.0.0rc2.data/data/share/jaqalpaq/tests/transpilers/qiskit/__init__.py
test_JaqalPaq_extras-0.0.1.1.0.0rc2.data/data/share/jaqalpaq/tests/transpilers/qiskit/test_qiskit_backend.py
test_JaqalPaq_extras-0.0.1.1.0.0rc2.data/data/share/jaqalpaq/tests/transpilers/qiskit/test_qiskit_gates.py
test_JaqalPaq_extras-0.0.1.1.0.0rc2.data/data/share/jaqalpaq/tests/transpilers/qiskit/test_qiskit_transpiler.py
test_JaqalPaq_extras-0.0.1.1.0.0rc2.data/data/share/jaqalpaq/tests/transpilers/qiskit/test_qiskit_unroller.py
test_JaqalPaq_extras-0.0.1.1.0.0rc2.dist-info/LICENSE
test_JaqalPaq_extras-0.0.1.1.0.0rc2.dist-info/METADATA
test_JaqalPaq_extras-0.0.1.1.0.0rc2.dist-info/NOTICE
test_JaqalPaq_extras-0.0.1.1.0.0rc2.dist-info/WHEEL
test_JaqalPaq_extras-0.0.1.1.0.0rc2.dist-info/top_level.txt
test_JaqalPaq_extras-0.0.1.1.0.0rc2.dist-info/RECORD
